{
  "date": "2026-07-07",
  "day": 3,
  "limits": {
    "total": 10,
    "new": 3,
    "review": 7
  },
  "items": [
    {
      "idx": 1,
      "qid": "2024-14",
      "year": "2024",
      "q": 14,
      "image": "bank/2024/q14.png",
      "answer_known": true,
      "source": "review"
    },
    {
      "idx": 2,
      "qid": "2025-01",
      "year": "2025",
      "q": 1,
      "image": "bank/2025/q01.png",
      "answer_known": true,
      "source": "review"
    },
    {
      "idx": 3,
      "qid": "2025-11",
      "year": "2025",
      "q": 11,
      "image": "bank/2025/q11.png",
      "answer_known": true,
      "source": "review"
    },
    {
      "idx": 4,
      "qid": "2024-33",
      "year": "2024",
      "q": 33,
      "image": "bank/2024/q33.png",
      "answer_known": true,
      "source": "review"
    },
    {
      "idx": 5,
      "qid": "2025-33",
      "year": "2025",
      "q": 33,
      "image": "bank/2025/q33.png",
      "answer_known": true,
      "source": "review"
    },
    {
      "idx": 6,
      "qid": "2024-15",
      "year": "2024",
      "q": 15,
      "image": "bank/2024/q15.png",
      "answer_known": true,
      "source": "review"
    },
    {
      "idx": 7,
      "qid": "2025-34",
      "year": "2025",
      "q": 34,
      "image": "bank/2025/q34.png",
      "answer_known": true,
      "source": "review"
    },
    {
      "idx": 8,
      "qid": "2025-18",
      "year": "2025",
      "q": 18,
      "image": "bank/2025/q18.png",
      "answer_known": true,
      "source": "new"
    },
    {
      "idx": 9,
      "qid": "2025-19",
      "year": "2025",
      "q": 19,
      "image": "bank/2025/q19.png",
      "answer_known": true,
      "source": "new"
    },
    {
      "idx": 10,
      "qid": "2025-20",
      "year": "2025",
      "q": 20,
      "image": "bank/2025/q20.png",
      "answer_known": true,
      "source": "new"
    }
  ]
}